vistral/__init__.py
vistral/__version__.py
vistral/command_bus/__init__.py
vistral/command_bus/command.py
vistral/command_bus/exceptions.py
vistral/command_bus/resolver.py
vistral/contrib/__init__.py
vistral/contrib/lagom.py
vistral/core/__init__.py
vistral/core/exceptions.py
vistral/py.typed
vistral-0.2.1.dist-info/METADATA
vistral-0.2.1.dist-info/WHEEL
vistral-0.2.1.dist-info/RECORD
