Metadata-Version: 2.1
Name: vistral
Version: 0.2.1
Summary: 
Author: Łukasz Wolak
Requires-Python: >=3.9,<4.0
Classifier: Programming Language :: Python :: 3
Classifier: Programming Language :: Python :: 3.9
Classifier: Programming Language :: Python :: 3.10
Classifier: Programming Language :: Python :: 3.11
Provides-Extra: lagom
Requires-Dist: lagom (>=2.4.1,<3.0.0) ; extra == "lagom"
